{"article_text": "Cycling|American Cyclist Wins Dubai Tourhttps://www.nytimes.com/2014/02/09/sports/cycling/american-cyclist-wins-dubai-tour.htmlSports BriefingFeb. 8, 2014Even a third straight stage win for Marcel Kittel of Germany was not enough to deny Taylor Phinney of the United States the overall victory in the inaugural Dubai Tour.Phinney played it safe in the sprint finish and successfully held on to the blue jersey that he got after winning the opening days individual time trial. He finished the tour 15 seconds ahead of his BMC Racing teammate Stephen Cummings. Garmin-Sharps Lasse Norman Hansen was third.", "generated_title": "American Cyclist Wins Dubai Tour", "publication_date": "2014-02-08", "primary_category": "sports", "content_type": "reporting", "keywords": ["cycling", "Dubai Tour", "Taylor Phinney", "Marcel Kittel", "BMC Racing", "Garmin-Sharp", "sports"], "mentioned_people": ["Taylor Phinney", "Marcel Kittel", "Stephen Cummings", "Lasse Norman Hansen"], "mentioned_organizations": ["BMC Racing", "Garmin-Sharp"], "mentioned_legislation": null, "mentioned_locations": ["Dubai"], "sentiment_tone": "neutral", "extracted_quotes": null, "snippet": "Taylor Phinney of the United States wins the inaugural Dubai Tour, finishing 15 seconds ahead of teammate Stephen Cummings."}